Workbook
Name aporte: Inicio!$D$17
Name qtd_anos: Inicio!$D$18
Name redimento_carteira: Inicio!$D$12

Sheet Inicio
B10: CONFIGURAÇÕES
B11: Salário | D11: 4200
B12: Rendimento Carteira | D12: 0.008
B13: Sugestão de Investimento (30%) | D13: =D11*30% -> 1260
B15: Investimento Mensal
B17: Quanto investir por mês? | D17: 200
B18: Por quantos anos? | D18: 5
B19: Taxa de rendimento mensal? | D19: =redimento_carteira -> 0.008
B20: Patrimônio acumulado? | D20: =FV(redimento_carteira,qtd_anos*12,aporte*-1) -> 15324.773
B21: Dividendos mensais? | D21: =D20*redimento_carteira -> 122.59819
B23: CENÁRIOS | C23: TOTAL | D23: DIVIDENDOS
A24: 2 | B24: Em 2 anos | C24: =FV(redimento_carteira,$A24*12,$D$17*-1) -> 5268.631 | D24: =C24*redimento_carteira -> 42.149048
A25: 5 | B25: Em 5 anos | C25: =FV(redimento_carteira,$A25*12,$D$17*-1) -> 15324.773 | D25: =C25*redimento_carteira -> 122.59819
A26: 10 | B26: Em 10 anos | C26: =FV(redimento_carteira,$A26*12,$D$17*-1) -> 40043.494 | D26: =C26*redimento_carteira -> 320.34795
A27: 20 | B27: Em 20 anos | C27: =FV(redimento_carteira,$A27*12,$D$17*-1) -> 144226.24 | D27: =C27*redimento_carteira -> 1153.81
A28: 30 | B28: Em 30 anos | C28: =FV(redimento_carteira,$A28*12,$D$17*-1) -> 415282.65 | D28: =C28*redimento_carteira -> 3322.2612
B30: PERFIL | C30: Moderado
B31: VALOR A SER INVESTIDO POR MÊS | C31: 200
B33: TIPO DE FII | C33: PERCENTUAL SUGERIDO | D33: VALORES
B34: PAPEL | C34: =VLOOKUP($C$30&"-"&B34,chaves!A:D,4,FALSE) -> 0.32 | D34: =$C$31*C34 -> 64
B35: TIJOLO | C35: =VLOOKUP($C$30&"-"&B35,chaves!A:D,4,FALSE) -> 0.4 | D35: =$C$31*C35 -> 80
B36: HÍBRIDOS | C36: =VLOOKUP($C$30&"-"&B36,chaves!A:D,4,FALSE) -> 0.05 | D36: =$C$31*C36 -> 10
B37: FOFs | C37: =VLOOKUP($C$30&"-"&B37,chaves!A:D,4,FALSE) -> 0.05 | D37: =$C$31*C37 -> 10
B38: DESENVOLVIMENTO | C38: =VLOOKUP($C$30&"-"&B38,chaves!A:D,4,FALSE) -> 0.08 | D38: =$C$31*C38 -> 16
B39: HOTELARIAS | C39: =VLOOKUP($C$30&"-"&B39,chaves!A:D,4,FALSE) -> 0.1 | D39: =$C$31*C39 -> 20

Sheet chaves
A2: Chaves | B2: Perfil | C2: tipo de fii | D2: %
A3: =B3&"-"&C3 -> Conservador-PAPEL | B3: Conservador | C3: PAPEL | D3: 0.3
A4: =B4&"-"&C4 -> Conservador-TIJOLO | B4: Conservador | C4: TIJOLO | D4: 0.5
A5: =B5&"-"&C5 -> Conservador-HÍBRIDOS | B5: Conservador | C5: HÍBRIDOS | D5: 0.1
A6: =B6&"-"&C6 -> Conservador-FOFs | B6: Conservador | C6: FOFs | D6: 0.1
A7: =B7&"-"&C7 -> Conservador-DESENVOLVIMENTO | B7: Conservador | C7: DESENVOLVIMENTO | D7: 0
A8: =B8&"-"&C8 -> Conservador-HOTELARIAS | B8: Conservador | C8: HOTELARIAS | D8: 0
A9: =B9&"-"&C9 -> Moderado-PAPEL | B9: Moderado | C9: PAPEL | D9: 0.32
A10: =B10&"-"&C10 -> Moderado-TIJOLO | B10: Moderado | C10: TIJOLO | D10: 0.4
A11: =B11&"-"&C11 -> Moderado-HÍBRIDOS | B11: Moderado | C11: HÍBRIDOS | D11: 0.05
A12: =B12&"-"&C12 -> Moderado-FOFs | B12: Moderado | C12: FOFs | D12: 0.05
A13: =B13&"-"&C13 -> Moderado-DESENVOLVIMENTO | B13: Moderado | C13: DESENVOLVIMENTO | D13: 0.08
A14: =B14&"-"&C14 -> Moderado-HOTELARIAS | B14: Moderado | C14: HOTELARIAS | D14: 0.1
... A20: =B20&"-"&C20 -> Agressivo-HOTELARIAS | B20: Agressivo | C20: HOTELARIAS | D20: 0.1
